fastapi_api_key/__init__.py
fastapi_api_key/__main__.py
fastapi_api_key/_types.py
fastapi_api_key/api.py
fastapi_api_key/cli.py
fastapi_api_key/py.typed
fastapi_api_key/utils.py
fastapi_api_key/domain/__init__.py
fastapi_api_key/domain/base.py
fastapi_api_key/domain/entities.py
fastapi_api_key/domain/errors.py
fastapi_api_key/hasher/__init__.py
fastapi_api_key/hasher/argon2.py
fastapi_api_key/hasher/base.py
fastapi_api_key/hasher/bcrypt.py
fastapi_api_key/repositories/__init__.py
fastapi_api_key/repositories/base.py
fastapi_api_key/repositories/in_memory.py
fastapi_api_key/repositories/sql.py
fastapi_api_key/services/__init__.py
fastapi_api_key/services/base.py
fastapi_api_key/services/cached.py
fastapi_api_key-1.1.0.dist-info/METADATA
fastapi_api_key-1.1.0.dist-info/WHEEL
fastapi_api_key-1.1.0.dist-info/entry_points.txt
fastapi_api_key-1.1.0.dist-info/licenses/LICENSE
fastapi_api_key-1.1.0.dist-info/RECORD
