Metadata-Version: 2.4
Name: fastapi-api-key
Version: 1.1.0
Summary: fastapi-api-key provides secure, production-ready API key management for FastAPI. It offers pluggable hashing strategies (Argon2 or bcrypt), backend-agnostic persistence (currently SQLAlchemy), and an optional cache layer (aiocache). Includes a Typer CLI and a FastAPI router for CRUD management of keys.
Project-URL: Homepage, https://github.com/Athroniaeth/fastapi-api-key
Project-URL: Documentation, https://github.com/Athroniaeth/fastapi-api-key#readme
Project-URL: Issues, https://github.com/Athroniaeth/fastapi-api-key/issues
Project-URL: Changelog, https://github.com/Athroniaeth/fastapi-api-key/blob/main/CHANGELOG.md
Author: Athroniaeth
License-File: LICENSE
Keywords: api,api key,authentication,authorization,backend-agnostic,fastapi,security,sqlalchemy,typer
Classifier: Environment :: Web Environment
Classifier: Framework :: FastAPI
Classifier: Intended Audience :: Developers
Classifier: License :: OSI Approved :: MIT License
Classifier: Programming Language :: Python :: 3
Classifier: Programming Language :: Python :: 3.9
Classifier: Programming Language :: Python :: 3.10
Classifier: Programming Language :: Python :: 3.11
Classifier: Programming Language :: Python :: 3.12
Classifier: Programming Language :: Python :: 3.13
Classifier: Programming Language :: Python :: 3.14
Classifier: Topic :: Internet :: WWW/HTTP
Classifier: Topic :: Security
Classifier: Topic :: Security :: Cryptography
Classifier: Typing :: Typed
Requires-Python: >=3.9
Provides-Extra: aiocache
Requires-Dist: aiocache>=0.12.0; extra == 'aiocache'
Provides-Extra: all
Requires-Dist: aiocache>=0.12.0; extra == 'all'
Requires-Dist: argon2-cffi>=23.1.0; extra == 'all'
Requires-Dist: bcrypt>=4.1.0; extra == 'all'
Requires-Dist: fastapi>=0.100.0; extra == 'all'
Requires-Dist: sqlalchemy>=2.0.0; extra == 'all'
Provides-Extra: argon2
Requires-Dist: argon2-cffi>=23.1.0; extra == 'argon2'
Provides-Extra: bcrypt
Requires-Dist: bcrypt>=4.1.0; extra == 'bcrypt'
Provides-Extra: cli
Requires-Dist: typer>=0.9.0; extra == 'cli'
Provides-Extra: core
Requires-Dist: aiocache>=0.12.0; extra == 'core'
Requires-Dist: argon2-cffi>=23.1.0; extra == 'core'
Requires-Dist: bcrypt>=4.1.0; extra == 'core'
Requires-Dist: sqlalchemy>=2.0.0; extra == 'core'
Provides-Extra: fastapi
Requires-Dist: fastapi>=0.100.0; extra == 'fastapi'
Provides-Extra: sqlalchemy
Requires-Dist: sqlalchemy>=2.0.0; extra == 'sqlalchemy'
